py_openapi_tools/__init__.py
py_openapi_tools/drf.py
py_openapi_tools/fastapi.py
py_openapi_tools/reader.py
py_openapi_tools/schema.py
py_openapi_tools/utils.py
py_openapi_tools-0.1.0.dist-info/METADATA
py_openapi_tools-0.1.0.dist-info/WHEEL
py_openapi_tools-0.1.0.dist-info/entry_points.txt
py_openapi_tools-0.1.0.dist-info/RECORD
