Metadata-Version: 2.4
Name: py-openapi-tools
Version: 0.1.0
Summary: Create files for various Python-Web-Frameworks from a OpenApi defintion.
Requires-Python: >=3.13
Requires-Dist: black>=25.11.0
Requires-Dist: hatchling>=1.28.0
Requires-Dist: isort
Requires-Dist: pytest>=9.0.1
Requires-Dist: pyyaml
Requires-Dist: ruff>=0.14.7
